pylearncode
